bigmodelvis/__init__.py
bigmodelvis/vis_logging.py
bigmodelvis/visualization.py
bigmodelvis-0.0.1.dist-info/LICENSE
bigmodelvis-0.0.1.dist-info/METADATA
bigmodelvis-0.0.1.dist-info/WHEEL
bigmodelvis-0.0.1.dist-info/top_level.txt
bigmodelvis-0.0.1.dist-info/RECORD
