Metadata-Version: 2.1
Name: bigmodelvis
Version: 0.0.1
Summary: A tool to visualize big models
Home-page: https://github.com/zt-wang19/bigmodelvis
Author: 
Author-email: shengdinghu@gmail.com
License: Apache
Keywords: transformers,Visualizaiton,AI,DeepLearning
Classifier: Programming Language :: Python :: 3
Classifier: Programming Language :: Python :: 3.8
Classifier: Programming Language :: Python :: 3.9
Classifier: Intended Audience :: Developers
Classifier: Intended Audience :: Education
Classifier: Intended Audience :: Science/Research
Classifier: License :: OSI Approved :: Apache Software License
Classifier: Operating System :: OS Independent
Requires-Python: >=3.6.0
License-File: LICENSE
Requires-Dist: torch (>=1.8.0)
Requires-Dist: transformers (>=4.10.0)
Requires-Dist: rich
